setup.py
Hawk.egg-info/PKG-INFO
Hawk.egg-info/SOURCES.txt
Hawk.egg-info/dependency_links.txt
Hawk.egg-info/entry_points.txt
Hawk.egg-info/requires.txt
Hawk.egg-info/top_level.txt
hawk/__init__.py
hawk/config.py
hawk/scripts.py
hawk/tinker.py