Metadata-Version: 1.0
Name: Hawk
Version: 0.1
Summary: Easy setup tool for Rackspace Cloud Monitoring
Home-page: https://github.com/vickleford/hawk
Author: Vic Watkins
Author-email: vic.watkins@rackspace.com
License: UNKNOWN
Platform: UNKNOWN
